vnpy_portfoliostrategy/__init__.py
vnpy_portfoliostrategy/backtesting.py
vnpy_portfoliostrategy/base.py
vnpy_portfoliostrategy/engine.py
vnpy_portfoliostrategy/template.py
vnpy_portfoliostrategy/utility.py
vnpy_portfoliostrategy/locale/__init__.py
vnpy_portfoliostrategy/locale/build_hook.py
vnpy_portfoliostrategy/locale/generate_mo.bat
vnpy_portfoliostrategy/locale/generate_pot.bat
vnpy_portfoliostrategy/locale/vnpy_portfoliostrategy.pot
vnpy_portfoliostrategy/locale/en/LC_MESSAGES/vnpy_portfoliostrategy.po
vnpy_portfoliostrategy/strategies/__init__.py
vnpy_portfoliostrategy/strategies/pair_trading_strategy.py
vnpy_portfoliostrategy/strategies/pcp_arbitrage_strategy.py
vnpy_portfoliostrategy/strategies/portfolio_boll_channel_strategy.py
vnpy_portfoliostrategy/strategies/trend_following_strategy.py
vnpy_portfoliostrategy/ui/__init__.py
vnpy_portfoliostrategy/ui/strategy.ico
vnpy_portfoliostrategy/ui/widget.py
vnpy_portfoliostrategy/locale/en/LC_MESSAGES/vnpy_portfoliostrategy.mo
vnpy_portfoliostrategy-1.2.2.dist-info/METADATA
vnpy_portfoliostrategy-1.2.2.dist-info/WHEEL
vnpy_portfoliostrategy-1.2.2.dist-info/licenses/LICENSE
vnpy_portfoliostrategy-1.2.2.dist-info/RECORD
